lirecouleur/__init__.py
lirecouleur/constant.py
lirecouleur/decoder.py
lirecouleur/parser.py
lirecouleur/text.py
lirecouleur/word.py
lirecouleur/appdata/automaton.json
lirecouleur/appdata/database.json
lirecouleur/appdata/dictionary.json
pylirecouleur-0.0.4.dist-info/LICENCE.md
pylirecouleur-0.0.4.dist-info/METADATA
pylirecouleur-0.0.4.dist-info/WHEEL
pylirecouleur-0.0.4.dist-info/top_level.txt
pylirecouleur-0.0.4.dist-info/RECORD
