Metadata-Version: 2.1
Name: pylirecouleur
Version: 0.0.4
Summary: Parse french texts into phonemes and syllables
Author-email: Marie-Pierre Brungard <lirecouleur@arkaline.fr>
Project-URL: Homepage, https://framagit.org/arkaline/pylirecouleur
Project-URL: Bug Tracker, https://framagit.org/arkaline/pylirecouleur/issues
Classifier: Programming Language :: Python :: 3
Classifier: License :: OSI Approved :: GNU General Public License v3 or later (GPLv3+)
Classifier: Operating System :: OS Independent
Classifier: Topic :: Education
Classifier: Natural Language :: French
Requires-Python: >=3.7
License-File: LICENCE.md
